jobfuscator/__init__.py
jobfuscator/jobfuscator.py
jobfuscator-1.0.4.dist-info/METADATA
jobfuscator-1.0.4.dist-info/WHEEL
jobfuscator-1.0.4.dist-info/top_level.txt
jobfuscator-1.0.4.dist-info/RECORD
