Metadata-Version: 2.1
Name: jobfuscator
Version: 1.0.4
Summary: JObfuscator is a source code obfuscator for the Java programming language. Obfuscate and protect your Java source code and algorithms from hacking, cracking, reverse engineering, decompilation, and technology theft. JObfuscator provides advanced Java source code parsing based on AST trees, multiple advanced obfuscation strategies are available.
Home-page: https://www.pelock.com
Author: Bartosz Wójcik
Author-email: support@pelock.com
License: Apache-2.0
Keywords: java jar war class source obfuscator obfuscation obfuscate decompile decompiler decompilation
Platform: UNKNOWN
Classifier: Development Status :: 5 - Production/Stable
Classifier: Topic :: Software Development :: Libraries :: Python Modules
Classifier: Topic :: Security
Classifier: Natural Language :: English
Classifier: License :: OSI Approved :: Apache Software License
Classifier: Programming Language :: Python :: 3
Classifier: Programming Language :: Java
Requires-Dist: requests
